hpb/__init__.py
hpb/__version__.py
hpb/main.py
hpb-0.0.1.dist-info/LICENSE
hpb-0.0.1.dist-info/METADATA
hpb-0.0.1.dist-info/WHEEL
hpb-0.0.1.dist-info/entry_points.txt
hpb-0.0.1.dist-info/top_level.txt
hpb-0.0.1.dist-info/RECORD
