Metadata-Version: 2.1
Name: hpb
Version: 0.0.1
Summary: Happy Package Builder
Author-email: Muggle Wei <mugglewei@gmail.com>
Project-URL: Homepage, https://github.com/MuggleWei/hpb
Project-URL: Bug Tracker, https://github.com/MuggleWei/hpb/issues
Keywords: dependency,libraries,package,artifacts,manager
Classifier: Programming Language :: Python :: 3
Classifier: License :: OSI Approved :: MIT License
Classifier: Operating System :: OS Independent
Requires-Python: >=3.7
License-File: LICENSE
Requires-Dist: pyyaml (==6.0)
Requires-Dist: distro (==1.8.0)
Requires-Dist: rich (==13.3.4)
